systembridgefrontend/__init__.py
systembridgefrontend/_version.py
systembridgefrontend/out/404.html
systembridgefrontend/out/favicon.svg
systembridgefrontend/out/index.html
systembridgefrontend/out/_next/static/chunks/171.392d4d1114914345.js
systembridgefrontend/out/_next/static/chunks/29107295-2a9ca7f07685bf37.js
systembridgefrontend/out/_next/static/chunks/373-1bdcaa87c1dc2325.js
systembridgefrontend/out/_next/static/chunks/457-873c7625be577093.js
systembridgefrontend/out/_next/static/chunks/561-962344efde9e9b34.js
systembridgefrontend/out/_next/static/chunks/699-2946d0281d10cb0d.js
systembridgefrontend/out/_next/static/chunks/734-2a07cd17442b7d52.js
systembridgefrontend/out/_next/static/chunks/75fc9c18-af385d3bdb0a9ad1.js
systembridgefrontend/out/_next/static/chunks/763-06be0e7bb698c0ec.js
systembridgefrontend/out/_next/static/chunks/8-fde3873dc4ccc337.js
systembridgefrontend/out/_next/static/chunks/826-0b778b2c0bd82cdc.js
systembridgefrontend/out/_next/static/chunks/870-8a5cb9241f2e30e6.js
systembridgefrontend/out/_next/static/chunks/873-fe06ac4f2740daa7.js
systembridgefrontend/out/_next/static/chunks/908-82ed3f6d6d9cd271.js
systembridgefrontend/out/_next/static/chunks/911-eccb307f97c99962.js
systembridgefrontend/out/_next/static/chunks/b2e984c5-2b1e013a93130176.js
systembridgefrontend/out/_next/static/chunks/framework-5429a50ba5373c56.js
systembridgefrontend/out/_next/static/chunks/main-fe015bc011991627.js
systembridgefrontend/out/_next/static/chunks/polyfills-c67a75d1b6f99dc8.js
systembridgefrontend/out/_next/static/chunks/reactPlayerDailyMotion.f8d751c322b8cf58.js
systembridgefrontend/out/_next/static/chunks/reactPlayerFacebook.2e01e00cea8f59fa.js
systembridgefrontend/out/_next/static/chunks/reactPlayerFilePlayer.c3db08fdc9b16652.js
systembridgefrontend/out/_next/static/chunks/reactPlayerKaltura.408e40ef9290cefa.js
systembridgefrontend/out/_next/static/chunks/reactPlayerMixcloud.2b627cc260c3eb52.js
systembridgefrontend-4.0.3.dist-info/LICENSE
systembridgefrontend-4.0.3.dist-info/METADATA
systembridgefrontend-4.0.3.dist-info/WHEEL
systembridgefrontend-4.0.3.dist-info/top_level.txt
systembridgefrontend-4.0.3.dist-info/RECORD
