Metadata-Version: 2.1
Name: systembridgefrontend
Version: 4.0.3
Summary: System Bridge Frontend
Home-page: https://github.com/timmo001/system-bridge-frontend
Author: Aidan Timson (Timmo)
Author-email: aidan@timmo.dev
License: Apache-2.0
Keywords: system-bridge
Requires-Python: >=3.11
License-File: LICENSE
